{
  "_source": "https://mientaycogi.com/danh-sach-chua-khmer-soc-trang-10212/",
  "_original_source": "Cổng Thông Tin Sóc Trăng (www.soctrang.gov.vn)",
  "_note": "93 Khmer pagodas in Sóc Trăng province with trilingual names (Pali-Khmer, common Khmer, Vietnamese)",
  "_crawl_date": "2026-04-09",
  "pagodas": [
    {"km_full": "Sêrey Cro Săng", "km_common": "Cro Săng", "vi": "Cà Săng", "year": 1576, "location": "Phường 2, Vĩnh Châu"},
    {"km_full": "MôniSakô ĐơmomPil", "km_common": "ĐomomPil", "vi": "Xẻo Me", "year": 1675, "location": "Phường Vĩnh Phước, Vĩnh Châu"},
    {"km_full": "Sêrey KanDal", "km_common": "KanDal", "vi": "KanDal", "year": 1694, "location": "Phường Vĩnh Phước, Vĩnh Châu"},
    {"km_full": "PíchMenKôl", "km_common": "Wáth Pích", "vi": "Wáth Pích", "year": 1738, "location": "Phường Vĩnh Phước, Vĩnh Châu"},
    {"km_full": "AmPôVon Soài Côn", "km_common": "Soài Côn", "vi": "Soài Côn", "year": 1750, "location": "Phường 2, Vĩnh Châu"},
    {"km_full": "ChhatTaVon Tăng Du", "km_common": "Tăng Du", "vi": "Tăng Dù", "year": 1771, "location": "Xã Lạc Hòa, Vĩnh Châu"},
    {"km_full": "Kompongmenchây Sêrey Prolean", "km_common": "ProLean", "vi": "ProLean", "year": 1773, "location": "Xã Vĩnh Hải, Vĩnh Châu"},
    {"km_full": "Môni SathaRam ĐôlTru", "km_common": "ĐôlTru", "vi": "Giồng Dú", "year": 1779, "location": "Phường 1, Vĩnh Châu"},
    {"km_full": "Pôthimengkôl Sêrey TaTeo", "km_common": "Ta Teo", "vi": "Tà Teo", "year": 1866, "location": "Xã Hòa Đông, Vĩnh Châu"},
    {"km_full": "Leskhanắsvong Chhung Thum", "km_common": "Chhung Thum", "vi": "Xung Thum", "year": 1872, "location": "Xã Lai Hòa, Vĩnh Châu"},
    {"km_full": "Sêrey TaSếk", "km_common": "TaSếk", "vi": "Tà Sết", "year": 1884, "location": "Xã Vĩnh Hải, Vĩnh Châu"},
    {"km_full": "Sêrey TaĐớk", "km_common": "TaĐớk", "vi": "Tà Đớt", "year": 1890, "location": "Xã Lạc Hòa, Vĩnh Châu"},
    {"km_full": "Tếp Pia Ram PrâyChop", "km_common": "Prây Chop", "vi": "Prây Chóp", "year": 1893, "location": "Xã Lai Hòa, Vĩnh Châu"},
    {"km_full": "BôTumSakô Sêrey PhnôPôl", "km_common": "PhnôPôl", "vi": "Nô Pôl", "year": 1896, "location": "Xã Vĩnh Tân, Vĩnh Châu"},
    {"km_full": "SalaPôthi Sêrey Sakô (Wáth Thmây)", "km_common": "Sala PôThi", "vi": "Chùa mới", "year": 1937, "location": "Phường 2, Vĩnh Châu"},
    {"km_full": "Sôvanh Kongke Muni Kos Tung", "km_common": "Kos Tung", "vi": "Kos Tung", "year": 1991, "location": "Xã An Thạnh 2, Cù Lao Dung"},
    {"km_full": "Compong Mengchay Tứkpray", "km_common": "Tứkpray", "vi": "Nước Mặn", "year": 1706, "location": "TT Long Phú, Long Phú"},
    {"km_full": "Sêrây Muni SăngKes", "km_common": "Săng Kes", "vi": "Săng Kes", "year": 1609, "location": "Xã Trường Khánh, Long Phú"},
    {"km_full": "Sêrây Ta Mơn", "km_common": "Ta Mơn", "vi": "Tà Mơn", "year": 1615, "location": "Xã Viên Bình, Trần Đề"},
    {"km_full": "Tak Khi Na Von Pô Thi Prưk", "km_common": "Prệc Côi Chăs", "vi": "Chùa Dơi", "year": 1502, "location": "TT Lịch Hội Thượng, Trần Đề"},
    {"km_full": "Kom Pung Menchây Sêrây Utđom Prêk Om Pu", "km_common": "Prêk Om Pu", "vi": "Tầm Du", "year": 1668, "location": "Xã Thạnh Thới An, Trần Đề"},
    {"km_full": "Can Đa Sô Phon Prêk On Đơk", "km_common": "Prêk On Đơk", "vi": "Cần Đước", "year": 1783, "location": "Xã Thạnh Phú, Mỹ Xuyên"},
    {"km_full": "Sêrây Sóckhum SongKum melchây Sro Lôn", "km_common": "Sro Lôn", "vi": "Chén Kiểu", "year": 1815, "location": "Xã Đại Tâm, Mỹ Xuyên"},
    {"km_full": "Pô Thi Sáth Chrôi Tưm Kal Đal", "km_common": "Chrôi Tưm Kal Đal", "vi": "Trà Tim Giữa", "year": 1666, "location": "Xã Đại Tâm, Mỹ Xuyên"},
    {"km_full": "Pra Sath Kong", "km_common": "Sath Kong", "vi": "Tắc Gồng", "year": 1224, "location": "Xã Tham Đôn, Mỹ Xuyên"},
    {"km_full": "Sêrây Utđom Phnô Kom Bôth", "km_common": "Phnô Kom Bôth", "vi": "Phnô Kom Bôth", "year": 1585, "location": "Xã Tham Đôn, Mỹ Xuyên"},
    {"km_full": "Hluông Ba Sắc Bai Chhau", "km_common": "Bai Chhau", "vi": "Bãi Xào", "year": 1507, "location": "TT Mỹ Xuyên, Mỹ Xuyên"},
    {"km_full": "ÔChum Maram Prêk Chêk", "km_common": "Prêk Chêk", "vi": "Prêk Chêk", "year": 1798, "location": "Xã Vĩnh Quới, Ngã Năm"},
    {"km_full": "Môni Sôphon Pong Tưk Chăs", "km_common": "Pong Tưk Chăs", "vi": "Pong Tưk Chăs", "year": 1830, "location": "Xã Thạnh Tân, Thạnh Trị"},
    {"km_full": "Sêrây Môni Vong Peng Som Rách", "km_common": "Peng Som Rách", "vi": "Peng Som Rách", "year": 1495, "location": "Xã An Hiệp, Châu Thành"},
    {"km_full": "Bô Tum Rengxây Tum Núp", "km_common": "Tum Núp", "vi": "Tum Núp", "year": 1621, "location": "Xã An Ninh, Châu Thành"},
    {"km_full": "Chăm Pa Vanhna Ram", "km_common": "Chăm Pa", "vi": "Chăm Pa", "year": 1676, "location": "Xã Phú Tân, Châu Thành"},
    {"km_full": "Pres Buôl Pres Phek", "km_common": "Pres Buôl Pres Phek", "vi": "Bốn mặt", "year": 1537, "location": "Xã Phú Tân, Châu Thành"},
    {"km_full": "Pô Thi Khsách", "km_common": "Pô Thi Khsách", "vi": "Pô Thi Khsách", "year": 1648, "location": "TT Kế Sách, Kế Sách"},
    {"km_full": "Ponhlư Pô Thi Onhđét Phđốt", "km_common": "Pô Thi Phđốt", "vi": "Pô Thi Phđốt", "year": 1618, "location": "Xã Kế Thành, Kế Sách"},
    {"km_full": "Sêrây Pôthiwel Pô Pus Tưk", "km_common": "Pô Pus Tưk", "vi": "Pô Pus Tưk", "year": 1901, "location": "Xã Phú Mỹ, Mỹ Tú"},
    {"km_full": "Puth Rengxây Bâng Kok", "km_common": "Bâng Kok", "vi": "Bưng Cóc", "year": 1727, "location": "Xã Phú Mỹ, Mỹ Tú"},
    {"km_full": "Sêrây Pô Thi Prưk Tà Ong", "km_common": "Tà Ong", "vi": "Tà Ong", "year": 1678, "location": "Xã Thuận Hưng, Mỹ Tú"},
    {"km_full": "Khleáng", "km_common": "Khleáng", "vi": "Khleáng", "year": 1533, "location": "Phường 6, TP Sóc Trăng"},
    {"km_full": "Bồtum Vongsa Som Rông", "km_common": "Som Rông", "vi": "Som Rông", "year": 1725, "location": "Phường 5, TP Sóc Trăng"},
    {"km_full": "Sêrây Têchô Ma Ha Túp", "km_common": "Ma Ha Túp", "vi": "Chùa Dơi", "year": 1569, "location": "Phường 3, TP Sóc Trăng"},
    {"km_full": "Maech Chhưm Meram Chrôi Tim Chăs", "km_common": "Chrôi Tim Chăs", "vi": "Trà Tim cũ", "year": 1465, "location": "Phường 10, TP Sóc Trăng"}
  ]
}
